sqlmodel_query_builder/__init__.py
sqlmodel_query_builder/_query_builder.py
sqlmodel_query_builder-0.1.0.dist-info/METADATA
sqlmodel_query_builder-0.1.0.dist-info/WHEEL
sqlmodel_query_builder-0.1.0.dist-info/RECORD
