Metadata-Version: 2.3
Name: sqlmodel-query-builder
Version: 0.1.0
Summary: A seriazable object for SQLModel queries
License: GPL-3.0
Author: Pedro Sader Azevedo
Author-email: pedro.saderazevedo@lnbr.cnpem.br
Requires-Python: >=3.12,<4.0
Classifier: License :: OSI Approved :: GNU General Public License v3 (GPLv3)
Classifier: Programming Language :: Python :: 3
Classifier: Programming Language :: Python :: 3.12
Classifier: Programming Language :: Python :: 3.13
Requires-Dist: pydantic (>=2.9.2,<3.0.0)
Requires-Dist: sqlmodel (>=0.0.22,<0.0.23)
